pytactor/__init__.py
pytactor/pytactor.py
pyTactor-0.1.4.dist-info/LICENSE
pyTactor-0.1.4.dist-info/METADATA
pyTactor-0.1.4.dist-info/WHEEL
pyTactor-0.1.4.dist-info/top_level.txt
pyTactor-0.1.4.dist-info/RECORD
