Metadata-Version: 2.1
Name: pyTactor
Version: 0.1.4
Summary: Control a vibrotactor array over BLE using Python code.
Home-page: https://github.com/Munroe-Meyer-Institute-VR-Laboratory/pyTactor
Author: Walker Arce
Author-email: walker.arce@unmc.edu
License: MIT
Keywords: BLE vibrotactor
Classifier: License :: OSI Approved :: MIT License
Classifier: Programming Language :: Python :: 3.8
License-File: LICENSE
Requires-Dist: adafruit-blinka-bleio
Requires-Dist: adafruit-circuitpython-ble
